{
  "_fv": 24,
  "_type": "recipe",
  "definition": {
    "recipeType": "Crafting",
    "xpReward": 0.0,
    "cookingTime": 200,
    "recipeRetstackSize": 1,
    "group": "",
    "recipeShapeless": false,
    "recipeSlots": [
      {
        "value": "CUSTOM:EmbossedTablet"
      },
      {
        "value": "TAG:elements_of_tantalus:etchers"
      },
      {
        "value": "CUSTOM:EmbossedTablet"
      },
      {
        "value": "Items.GOLD_INGOT"
      },
      {
        "value": "CUSTOM:EmbossedTantalusHeart"
      },
      {
        "value": "Items.GOLD_INGOT"
      },
      {
        "value": "CUSTOM:EmbossedTablet"
      },
      {
        "value": "Blocks.GOLD_BLOCK"
      },
      {
        "value": "CUSTOM:EmbossedTablet"
      }
    ],
    "recipeReturnStack": {
      "value": "CUSTOM:EmbossedInscriptionTable"
    },
    "name": "craft_inscriber_3",
    "namespace": "mod"
  }
}